webchk/__init__.py
webchk/__main__.py
webchk/http.py
webchk/utils.py
webchk-1.2.0.dist-info/AUTHORS.rst
webchk-1.2.0.dist-info/LICENSE
webchk-1.2.0.dist-info/METADATA
webchk-1.2.0.dist-info/WHEEL
webchk-1.2.0.dist-info/entry_points.txt
webchk-1.2.0.dist-info/top_level.txt
webchk-1.2.0.dist-info/RECORD
