Metadata-Version: 2.1
Name: webchk
Version: 1.2.0
Summary: A command-line tool for checking HTTP status codes and response headers of URLs
Home-page: https://webchk.codehill.com
Author: Amged Rustom
Author-email: amgadhs@codehill.com
License: MIT license
Keywords: webchk site management www http link check
Platform: UNKNOWN
Classifier: Development Status :: 5 - Production/Stable
Classifier: Environment :: Console
Classifier: Intended Audience :: Developers
Classifier: Programming Language :: Python :: 3
Classifier: Programming Language :: Python :: 3.4
Classifier: Programming Language :: Python :: 3.5
Classifier: Programming Language :: Python :: 3.6
Classifier: Programming Language :: Python :: 3.7
Classifier: Programming Language :: Python :: 3.8
Classifier: Programming Language :: Python :: Implementation :: CPython
Classifier: Topic :: Internet :: WWW/HTTP
Classifier: Topic :: Internet :: WWW/HTTP :: Site Management
Classifier: Topic :: Internet :: WWW/HTTP :: Site Management :: Link Checking
Classifier: Intended Audience :: Developers
Classifier: Intended Audience :: System Administrators
